
{
    "topologies":
    [
        {
            "name": "ImagingSatConstellation",
            "id": 0,
            "nodes":
            [
    
                {
                    "type": "SAT",
                    "iname": "SatelliteBasic",
                    "nodeid": 1,
                    "loglevel": "info",
                    "tle_1": "1 49439U 21104AH  24101.19748631  .00002083  00000+0  16708-4 0  9992", 
                    "tle_2": "2 49439  53.2071  67.2274 0001136  79.2676 280.8473 15.76746119135081",
                    "additionalargs": "",
                    "models":[
                        {
                            "iname": "ModelOrbit"
                        },
                        {
                            "iname": "ModelFovTimeBased",
                            "min_elevation": 25
                        },
                        {
                            "iname": "simplemodel"
                        }
                        
                    ]
                },

                {
                    "type": "SAT",
                    "iname": "SatelliteBasic",
                    "nodeid": 3,
                    "loglevel": "info",
                    "tle_1": "1 52378U 22045AZ  24101.36860983  .00000145  00000+0  27228-4 0  9993", 
                    "tle_2": "2 52378  53.2171  84.0024 0001498  96.9627 263.1535 15.08841622110504",
                    "additionalargs": "",
                    "models":[
                        {
                            "iname": "ModelOrbit"
                        },
                        {
                            "iname": "ModelFovTimeBased",
                            "min_elevation": 25
                        },
                        {
                            "iname": "simplemodel"
                        }
                        
                    ]
                },

                {
                    "type": "SAT",
                    "iname": "SatelliteBasic",
                    "nodeid": 5,
                    "loglevel": "info",
                    "tle_1": "1 45663U 20035G   24100.89509265  .00005465  00000+0  38530-3 0  9996", 
                    "tle_2": "2 45663  53.0560 323.6272 0001125 103.1993 256.9121 15.06419223213404",
                    "additionalargs": "",
                    "models":[
                        {
                            "iname": "ModelOrbit"
                        },
                        {
                            "iname": "ModelFovTimeBased",
                            "min_elevation": 25
                        },
                        {
                            "iname": "simplemodel"
                        }
                        
                    ]
                },

                {
                    "type": "SAT",
                    "iname": "SatelliteBasic",
                    "nodeid": 7,
                    "loglevel": "info",
                    "tle_1": "1 55618U 23020BB  24101.22310236  .00000691  00000+0  66227-4 0  9991", 
                    "tle_2": "2 55618  43.0045 186.7804 0001153 271.9307  88.1403 15.02534872 64007",
                    "additionalargs": "",
                    "models":[
                        {
                            "iname": "ModelOrbit"
                        },
                        {
                            "iname": "ModelFovTimeBased",
                            "min_elevation": 25
                        },
                        {
                            "iname": "simplemodel"
                        }
                        
                    ]
                },

                {
                    "type": "SAT",
                    "iname": "SatelliteBasic",
                    "nodeid": 9,
                    "loglevel": "info",
                    "tle_1": "1 53632U 22104AW  24101.44083313  .00000726  00000+0  63732-4 0  9991", 
                    "tle_2": "2 53632  53.2166 118.6675 0001421  95.9050 264.2104 15.08839840 89792",
                    "additionalargs": "",
                    "models":[
                        {
                            "iname": "ModelOrbit"
                        },
                        {
                            "iname": "ModelFovTimeBased",
                            "min_elevation": 25
                        },
                        {
                            "iname": "simplemodel"
                        }
                        
                    ]
                },

                {
                    "type": "SAT",
                    "iname": "SatelliteBasic",
                    "nodeid": 11,
                    "loglevel": "info",
                    "tle_1": "1 50193U 21125AP  24101.40817287  .00000964  00000+0  78613-4 0  9991", 
                    "tle_2": "2 50193  53.2162 133.8286 0001431  92.1001 268.0155 15.08843408130835",
                    "additionalargs": "",
                    "models":[
                        {
                            "iname": "ModelOrbit"
                        },
                        {
                            "iname": "ModelFovTimeBased",
                            "min_elevation": 25
                        },
                        {
                            "iname": "simplemodel"
                        }
                        
                    ]
                },

                {
                    "type": "SAT",
                    "iname": "SatelliteBasic",
                    "nodeid": 13,
                    "loglevel": "info",
                    "tle_1": "1 56137U 23046AX  24101.06464806  .00000607  00000+0  60035-4 0  9999", 
                    "tle_2": "2 56137  43.0046 341.8425 0001059 269.4951  90.5770 15.02536342 57662",
                    "additionalargs": "",
                    "models":[
                        {
                            "iname": "ModelOrbit"
                        },
                        {
                            "iname": "ModelFovTimeBased",
                            "min_elevation": 25
                        },
                        {
                            "iname": "simplemodel"
                        }
                        
                    ]
                },

                {
                    "type": "SAT",
                    "iname": "SatelliteBasic",
                    "nodeid": 15,
                    "loglevel": "info",
                    "tle_1": "1 53729U 22107AF  24100.86768178  .00001065  00000+0  84995-4 0  9996", 
                    "tle_2": "2 53729  53.2169 151.3659 0001317  84.9341 275.1801 15.08843072 89082",
                    "additionalargs": "",
                    "models":[
                        {
                            "iname": "ModelOrbit"
                        },
                        {
                            "iname": "ModelFovTimeBased",
                            "min_elevation": 25
                        },
                        {
                            "iname": "simplemodel"
                        }
                        
                    ]
                },

                {
                    "type": "SAT",
                    "iname": "SatelliteBasic",
                    "nodeid": 17,
                    "loglevel": "info",
                    "tle_1": "1 57102U 23090B   24101.49851189 -.00000027  00000+0  13073-4 0  9999", 
                    "tle_2": "2 57102  43.0028 108.7417 0001230 267.3576  92.7125 15.02532569 44242",
                    "additionalargs": "",
                    "models":[
                        {
                            "iname": "ModelOrbit"
                        },
                        {
                            "iname": "ModelFovTimeBased",
                            "min_elevation": 25
                        },
                        {
                            "iname": "simplemodel"
                        }
                        
                    ]
                },

                {
                    "type": "SAT",
                    "iname": "SatelliteBasic",
                    "nodeid": 19,
                    "loglevel": "info",
                    "tle_1": "1 53157U 22083AB  24101.14827387  .00000327  00000+0  38612-4 0  9999", 
                    "tle_2": "2 53157  53.2198  59.9933 0001279  87.7073 272.4066 15.08837502 96539",
                    "additionalargs": "",
                    "models":[
                        {
                            "iname": "ModelOrbit"
                        },
                        {
                            "iname": "ModelFovTimeBased",
                            "min_elevation": 25
                        },
                        {
                            "iname": "simplemodel"
                        }
                        
                    ]
                },

                {
                    "type": "SAT",
                    "iname": "SatelliteBasic",
                    "nodeid": 21,
                    "loglevel": "info",
                    "tle_1": "1 56837U 23079Q   24101.24939061  .00000597  00000+0  59291-4 0  9992", 
                    "tle_2": "2 56837  43.0033 302.2488 0002172 268.2305  91.8288 15.02541994 47499",
                    "additionalargs": "",
                    "models":[
                        {
                            "iname": "ModelOrbit"
                        },
                        {
                            "iname": "ModelFovTimeBased",
                            "min_elevation": 25
                        },
                        {
                            "iname": "simplemodel"
                        }
                        
                    ]
                },

                {
                    "type": "SAT",
                    "iname": "SatelliteBasic",
                    "nodeid": 23,
                    "loglevel": "info",
                    "tle_1": "1 53973U 22125K   24100.78945300  .00001258  00000+0  97118-4 0  9997", 
                    "tle_2": "2 53973  53.2166 121.4835 0001463  91.3810 268.7350 15.08844320 83818",
                    "additionalargs": "",
                    "models":[
                        {
                            "iname": "ModelOrbit"
                        },
                        {
                            "iname": "ModelFovTimeBased",
                            "min_elevation": 25
                        },
                        {
                            "iname": "simplemodel"
                        }
                        
                    ]
                },

                {
                    "type": "SAT",
                    "iname": "SatelliteBasic",
                    "nodeid": 25,
                    "loglevel": "info",
                    "tle_1": "1 57345U 23099T   24100.31237812  .00000533  00000+0  54542-4 0  9995", 
                    "tle_2": "2 57345  43.0046  89.0564 0001293 275.3646  84.7049 15.02534248 40913",
                    "additionalargs": "",
                    "models":[
                        {
                            "iname": "ModelOrbit"
                        },
                        {
                            "iname": "ModelFovTimeBased",
                            "min_elevation": 25
                        },
                        {
                            "iname": "simplemodel"
                        }
                        
                    ]
                },

                {
                    "type": "SAT",
                    "iname": "SatelliteBasic",
                    "nodeid": 27,
                    "loglevel": "info",
                    "tle_1": "1 47846U 21018BM  24101.25001157 -.00025717  00000+0 -19885-3 0  9997", 
                    "tle_2": "2 47846  53.0526 134.8355 0001598  91.7240 169.8805 15.70782521171157",
                    "additionalargs": "",
                    "models":[
                        {
                            "iname": "ModelOrbit"
                        },
                        {
                            "iname": "ModelFovTimeBased",
                            "min_elevation": 25
                        },
                        {
                            "iname": "simplemodel"
                        }
                        
                    ]
                },

                {
                    "type": "SAT",
                    "iname": "SatelliteBasic",
                    "nodeid": 29,
                    "loglevel": "info",
                    "tle_1": "1 52543U 22051L   24101.52134588 -.00002010  00000+0 -10826-3 0  9997", 
                    "tle_2": "2 52543  53.2180  23.3199 0001345  81.4034 278.7110 15.08827959106119",
                    "additionalargs": "",
                    "models":[
                        {
                            "iname": "ModelOrbit"
                        },
                        {
                            "iname": "ModelFovTimeBased",
                            "min_elevation": 25
                        },
                        {
                            "iname": "simplemodel"
                        }
                        
                    ]
                },

                {
                    "type": "SAT",
                    "iname": "SatelliteBasic",
                    "nodeid": 31,
                    "loglevel": "info",
                    "tle_1": "1 58804U 24012T   24101.13046192  .00007446  00000+0  29417-3 0  9994", 
                    "tle_2": "2 58804  42.9984 143.1873 0000233 212.6581 147.4255 15.25912352 14494",
                    "additionalargs": "",
                    "models":[
                        {
                            "iname": "ModelOrbit"
                        },
                        {
                            "iname": "ModelFovTimeBased",
                            "min_elevation": 25
                        },
                        {
                            "iname": "simplemodel"
                        }
                        
                    ]
                },

                {
                    "type": "SAT",
                    "iname": "SatelliteBasic",
                    "nodeid": 33,
                    "loglevel": "info",
                    "tle_1": "1 58012U 23153X   24101.48629793 -.00008422  00000+0 -60882-3 0  9990", 
                    "tle_2": "2 58012  43.0021 262.9791 0001147 285.6467  74.4249 15.02556793 29841",
                    "additionalargs": "",
                    "models":[
                        {
                            "iname": "ModelOrbit"
                        },
                        {
                            "iname": "ModelFovTimeBased",
                            "min_elevation": 25
                        },
                        {
                            "iname": "simplemodel"
                        }
                        
                    ]
                },

                {
                    "type": "SAT",
                    "iname": "SatelliteBasic",
                    "nodeid": 35,
                    "loglevel": "info",
                    "tle_1": "1 58972U 24031H   24101.26089189  .00002916  00000+0  11785-3 0  9994", 
                    "tle_2": "2 58972  53.1575 300.6208 0000636 114.1000 246.0066 15.28026488  9647",
                    "additionalargs": "",
                    "models":[
                        {
                            "iname": "ModelOrbit"
                        },
                        {
                            "iname": "ModelFovTimeBased",
                            "min_elevation": 25
                        },
                        {
                            "iname": "simplemodel"
                        }
                        
                    ]
                },

                {
                    "type": "SAT",
                    "iname": "SatelliteBasic",
                    "nodeid": 37,
                    "loglevel": "info",
                    "tle_1": "1 57674U 23124M   24101.58335648 -.00071779  00000+0 -26024-2 0  9999", 
                    "tle_2": "2 57674  53.1226 212.2633 0001576  84.5272   8.3875 15.28036688 36294",
                    "additionalargs": "",
                    "models":[
                        {
                            "iname": "ModelOrbit"
                        },
                        {
                            "iname": "ModelFovTimeBased",
                            "min_elevation": 25
                        },
                        {
                            "iname": "simplemodel"
                        }
                        
                    ]
                },

                {
                    "type": "SAT",
                    "iname": "SatelliteBasic",
                    "nodeid": 39,
                    "loglevel": "info",
                    "tle_1": "1 54053U 22136C   24101.40405353  .00000526  00000+0  51117-4 0  9994", 
                    "tle_2": "2 54053  53.2113 239.0521 0001512  91.5735 268.5431 15.08839762 81901",
                    "additionalargs": "",
                    "models":[
                        {
                            "iname": "ModelOrbit"
                        },
                        {
                            "iname": "ModelFovTimeBased",
                            "min_elevation": 25
                        },
                        {
                            "iname": "simplemodel"
                        }
                        
                    ]
                },

                {
                    "type": "SAT",
                    "iname": "SatelliteBasic",
                    "nodeid": 41,
                    "loglevel": "info",
                    "tle_1": "1 57376U 23099BA  24101.22889178 -.00000447  00000+0 -17986-4 0  9995", 
                    "tle_2": "2 57376  43.0039  70.8607 0001282 271.5086  88.5609 15.02527606 41947",
                    "additionalargs": "",
                    "models":[
                        {
                            "iname": "ModelOrbit"
                        },
                        {
                            "iname": "ModelFovTimeBased",
                            "min_elevation": 25
                        },
                        {
                            "iname": "simplemodel"
                        }
                        
                    ]
                },

                {
                    "type": "SAT",
                    "iname": "SatelliteBasic",
                    "nodeid": 43,
                    "loglevel": "info",
                    "tle_1": "1 48100U 21027J   24101.15448700  .00001243  00000+0  10234-3 0  9994", 
                    "tle_2": "2 48100  53.0555  47.4618 0001511  96.1133 264.0028 15.06407812167010",
                    "additionalargs": "",
                    "models":[
                        {
                            "iname": "ModelOrbit"
                        },
                        {
                            "iname": "ModelFovTimeBased",
                            "min_elevation": 25
                        },
                        {
                            "iname": "simplemodel"
                        }
                        
                    ]
                },

                {
                    "type": "SAT",
                    "iname": "SatelliteBasic",
                    "nodeid": 45,
                    "loglevel": "info",
                    "tle_1": "1 44961U 20001AZ  24100.99093786  .00007588  00000+0  52760-3 0  9995", 
                    "tle_2": "2 44961  53.0554 203.1993 0001480  96.2543 263.8614 15.06408400235106",
                    "additionalargs": "",
                    "models":[
                        {
                            "iname": "ModelOrbit"
                        },
                        {
                            "iname": "ModelFovTimeBased",
                            "min_elevation": 25
                        },
                        {
                            "iname": "simplemodel"
                        }
                        
                    ]
                },

                {
                    "type": "SAT",
                    "iname": "SatelliteBasic",
                    "nodeid": 47,
                    "loglevel": "info",
                    "tle_1": "1 55933U 23037V   24101.41916755 -.00000575  00000+0 -40430-4 0  9999", 
                    "tle_2": "2 55933  70.0046 245.1393 0003063 270.0420  90.0388 14.98333674 59727",
                    "additionalargs": "",
                    "models":[
                        {
                            "iname": "ModelOrbit"
                        },
                        {
                            "iname": "ModelFovTimeBased",
                            "min_elevation": 25
                        },
                        {
                            "iname": "simplemodel"
                        }
                        
                    ]
                },

                {
                    "type": "SAT",
                    "iname": "SatelliteBasic",
                    "nodeid": 49,
                    "loglevel": "info",
                    "tle_1": "1 54100U 22136BB  24100.62843436 -.00000290  00000+0 -10595-6 0  9995", 
                    "tle_2": "2 54100  53.2157 232.0383 0001473  84.8230 275.2930 15.08848026 81926",
                    "additionalargs": "",
                    "models":[
                        {
                            "iname": "ModelOrbit"
                        },
                        {
                            "iname": "ModelFovTimeBased",
                            "min_elevation": 25
                        },
                        {
                            "iname": "simplemodel"
                        }
                        
                    ]
                },

                {
                    "type": "SAT",
                    "iname": "SatelliteBasic",
                    "nodeid": 51,
                    "loglevel": "info",
                    "tle_1": "1 49435U 21104AD  24101.26836500  .00001301  00000+0  99787-4 0  9999", 
                    "tle_2": "2 49435  53.2162 104.4552 0001578  86.8026 273.3147 15.08846756134553",
                    "additionalargs": "",
                    "models":[
                        {
                            "iname": "ModelOrbit"
                        },
                        {
                            "iname": "ModelFovTimeBased",
                            "min_elevation": 25
                        },
                        {
                            "iname": "simplemodel"
                        }
                        
                    ]
                },

                {
                    "type": "SAT",
                    "iname": "SatelliteBasic",
                    "nodeid": 53,
                    "loglevel": "info",
                    "tle_1": "1 58474U 23186B   24101.48239158  .00023312  00000+0  89803-3 0  9997", 
                    "tle_2": "2 58474  43.0023 251.0760 0004046 284.7605  75.2798 15.25911710 20898",
                    "additionalargs": "",
                    "models":[
                        {
                            "iname": "ModelOrbit"
                        },
                        {
                            "iname": "ModelFovTimeBased",
                            "min_elevation": 25
                        },
                        {
                            "iname": "simplemodel"
                        }
                        
                    ]
                },

                {
                    "type": "SAT",
                    "iname": "SatelliteBasic",
                    "nodeid": 55,
                    "loglevel": "info",
                    "tle_1": "1 59180U 24045C   24101.47790048  .00016740  00000+0  40672-3 0  9994", 
                    "tle_2": "2 59180  42.9998 110.7527 0001475 231.2084 128.8641 15.40730310  5971",
                    "additionalargs": "",
                    "models":[
                        {
                            "iname": "ModelOrbit"
                        },
                        {
                            "iname": "ModelFovTimeBased",
                            "min_elevation": 25
                        },
                        {
                            "iname": "simplemodel"
                        }
                        
                    ]
                },

                {
                    "type": "SAT",
                    "iname": "SatelliteBasic",
                    "nodeid": 57,
                    "loglevel": "info",
                    "tle_1": "1 58242U 23171N   24101.45463239  .00000480  00000+0  50613-4 0  9999", 
                    "tle_2": "2 58242  43.0027 119.9229 0001265 270.1000  89.9698 15.02537214 24719",
                    "additionalargs": "",
                    "models":[
                        {
                            "iname": "ModelOrbit"
                        },
                        {
                            "iname": "ModelFovTimeBased",
                            "min_elevation": 25
                        },
                        {
                            "iname": "simplemodel"
                        }
                        
                    ]
                },

                {
                    "type": "SAT",
                    "iname": "SatelliteBasic",
                    "nodeid": 59,
                    "loglevel": "info",
                    "tle_1": "1 56886U 23083L   24101.49708344  .00001307  00000+0  11183-3 0  9993", 
                    "tle_2": "2 56886  43.0047 275.6030 0001444 271.9453  88.1224 15.02538591 45845",
                    "additionalargs": "",
                    "models":[
                        {
                            "iname": "ModelOrbit"
                        },
                        {
                            "iname": "ModelFovTimeBased",
                            "min_elevation": 25
                        },
                        {
                            "iname": "simplemodel"
                        }
                        
                    ]
                },

                {
                    "type": "SAT",
                    "iname": "SatelliteBasic",
                    "nodeid": 61,
                    "loglevel": "info",
                    "tle_1": "1 49744U 21115W   24100.26555411  .00000551  00000+0  52720-4 0  9994", 
                    "tle_2": "2 49744  53.2195  48.8483 0001537  89.8759 270.2409 15.08841471129940",
                    "additionalargs": "",
                    "models":[
                        {
                            "iname": "ModelOrbit"
                        },
                        {
                            "iname": "ModelFovTimeBased",
                            "min_elevation": 25
                        },
                        {
                            "iname": "simplemodel"
                        }
                        
                    ]
                },

                {
                    "type": "SAT",
                    "iname": "SatelliteBasic",
                    "nodeid": 63,
                    "loglevel": "info",
                    "tle_1": "1 55337U 23013G   24100.44005795  .00001638  00000+0  13628-3 0  9993", 
                    "tle_2": "2 55337  43.0027 126.8465 0001236 270.0705  89.9996 15.02535762 66677",
                    "additionalargs": "",
                    "models":[
                        {
                            "iname": "ModelOrbit"
                        },
                        {
                            "iname": "ModelFovTimeBased",
                            "min_elevation": 25
                        },
                        {
                            "iname": "simplemodel"
                        }
                        
                    ]
                },

                {
                    "type": "SAT",
                    "iname": "SatelliteBasic",
                    "nodeid": 65,
                    "loglevel": "info",
                    "tle_1": "1 53145U 22083P   24101.33134851  .00000246  00000+0  33527-4 0  9994", 
                    "tle_2": "2 53145  53.2186  69.1716 0001413  93.0177 267.0977 15.08840589 96428",
                    "additionalargs": "",
                    "models":[
                        {
                            "iname": "ModelOrbit"
                        },
                        {
                            "iname": "ModelFovTimeBased",
                            "min_elevation": 25
                        },
                        {
                            "iname": "simplemodel"
                        }
                        
                    ]
                },

                {
                    "type": "SAT",
                    "iname": "SatelliteBasic",
                    "nodeid": 67,
                    "loglevel": "info",
                    "tle_1": "1 55657U 23021AF  24101.20080563  .00000489  00000+0  48783-4 0  9992", 
                    "tle_2": "2 55657  69.9985 125.7596 0003432 267.6333  92.4433 14.98329599 64355",
                    "additionalargs": "",
                    "models":[
                        {
                            "iname": "ModelOrbit"
                        },
                        {
                            "iname": "ModelFovTimeBased",
                            "min_elevation": 25
                        },
                        {
                            "iname": "simplemodel"
                        }
                        
                    ]
                },

                {
                    "type": "SAT",
                    "iname": "SatelliteBasic",
                    "nodeid": 69,
                    "loglevel": "info",
                    "tle_1": "1 47361U 21005N   24101.22084607  .00000861  00000+0  76700-4 0  9994", 
                    "tle_2": "2 47361  53.0534 287.1626 0001796  84.1311 275.9883 15.06395828179136",
                    "additionalargs": "",
                    "models":[
                        {
                            "iname": "ModelOrbit"
                        },
                        {
                            "iname": "ModelFovTimeBased",
                            "min_elevation": 25
                        },
                        {
                            "iname": "simplemodel"
                        }
                        
                    ]
                },

                {
                    "type": "SAT",
                    "iname": "SatelliteBasic",
                    "nodeid": 71,
                    "loglevel": "info",
                    "tle_1": "1 58799U 24012N   24101.49437487  .00019924  00000+0  49556-3 0  9997", 
                    "tle_2": "2 58799  43.0004 135.5735 0009094  83.0544 277.1347 15.39883231 14511",
                    "additionalargs": "",
                    "models":[
                        {
                            "iname": "ModelOrbit"
                        },
                        {
                            "iname": "ModelFovTimeBased",
                            "min_elevation": 25
                        },
                        {
                            "iname": "simplemodel"
                        }
                        
                    ]
                },

                {
                    "type": "SAT",
                    "iname": "SatelliteBasic",
                    "nodeid": 73,
                    "loglevel": "info",
                    "tle_1": "1 57603U 23119B   24100.86774115  .00000125  00000+0  24352-4 0  9990", 
                    "tle_2": "2 57603  43.0013 278.9166 0001250 261.5860  98.4841 15.02541209 37956",
                    "additionalargs": "",
                    "models":[
                        {
                            "iname": "ModelOrbit"
                        },
                        {
                            "iname": "ModelFovTimeBased",
                            "min_elevation": 25
                        },
                        {
                            "iname": "simplemodel"
                        }
                        
                    ]
                },

                {
                    "type": "SAT",
                    "iname": "SatelliteBasic",
                    "nodeid": 75,
                    "loglevel": "info",
                    "tle_1": "1 59213U 24046N   24101.58335648  .00050009  00000+0  11266-2 0  9997", 
                    "tle_2": "2 59213  53.1592 171.7105 0001251  86.9910 251.3991 15.42804872  5748",
                    "additionalargs": "",
                    "models":[
                        {
                            "iname": "ModelOrbit"
                        },
                        {
                            "iname": "ModelFovTimeBased",
                            "min_elevation": 25
                        },
                        {
                            "iname": "simplemodel"
                        }
                        
                    ]
                },

                {
                    "type": "SAT",
                    "iname": "SatelliteBasic",
                    "nodeid": 77,
                    "loglevel": "info",
                    "tle_1": "1 53256U 22086Q   24101.25958510 -.00001100  00000+0 -51058-4 0  9998", 
                    "tle_2": "2 53256  53.2180  89.4959 0001369  89.4754 270.6395 15.08834229 95448",
                    "additionalargs": "",
                    "models":[
                        {
                            "iname": "ModelOrbit"
                        },
                        {
                            "iname": "ModelFovTimeBased",
                            "min_elevation": 25
                        },
                        {
                            "iname": "simplemodel"
                        }
                        
                    ]
                },

                {
                    "type": "SAT",
                    "iname": "SatelliteBasic",
                    "nodeid": 79,
                    "loglevel": "info",
                    "tle_1": "1 53550U 22101Z   24100.90723338  .00000211  00000+0  31355-4 0  9990", 
                    "tle_2": "2 53550  53.2200 321.0803 0001916 101.7612 258.3595 15.08836955 90819",
                    "additionalargs": "",
                    "models":[
                        {
                            "iname": "ModelOrbit"
                        },
                        {
                            "iname": "ModelFovTimeBased",
                            "min_elevation": 25
                        },
                        {
                            "iname": "simplemodel"
                        }
                        
                    ]
                },

                {
                    "type": "SAT",
                    "iname": "SatelliteBasic",
                    "nodeid": 81,
                    "loglevel": "info",
                    "tle_1": "1 52847U 22062T   24101.21175082  .00000331  00000+0  38876-4 0  9994", 
                    "tle_2": "2 52847  53.2193 289.7115 0001591  88.9147 271.2027 15.08840782100833",
                    "additionalargs": "",
                    "models":[
                        {
                            "iname": "ModelOrbit"
                        },
                        {
                            "iname": "ModelFovTimeBased",
                            "min_elevation": 25
                        },
                        {
                            "iname": "simplemodel"
                        }
                        
                    ]
                },

                {
                    "type": "SAT",
                    "iname": "SatelliteBasic",
                    "nodeid": 83,
                    "loglevel": "info",
                    "tle_1": "1 49430U 21104Y   24100.79551954  .00002762  00000+0  19150-3 0  9995", 
                    "tle_2": "2 49430  53.2155 126.8590 0001432  84.3728 275.7427 15.08847443133124",
                    "additionalargs": "",
                    "models":[
                        {
                            "iname": "ModelOrbit"
                        },
                        {
                            "iname": "ModelFovTimeBased",
                            "min_elevation": 25
                        },
                        {
                            "iname": "simplemodel"
                        }
                        
                    ]
                },

                {
                    "type": "SAT",
                    "iname": "SatelliteBasic",
                    "nodeid": 85,
                    "loglevel": "info",
                    "tle_1": "1 53915U 22119AF  24100.72600657  .00001470  00000+0  11044-3 0  9992", 
                    "tle_2": "2 53915  53.2195 211.9918 0001467  90.6367 269.4793 15.08840592 86309",
                    "additionalargs": "",
                    "models":[
                        {
                            "iname": "ModelOrbit"
                        },
                        {
                            "iname": "ModelFovTimeBased",
                            "min_elevation": 25
                        },
                        {
                            "iname": "simplemodel"
                        }
                        
                    ]
                },

                {
                    "type": "SAT",
                    "iname": "SatelliteBasic",
                    "nodeid": 87,
                    "loglevel": "info",
                    "tle_1": "1 53165U 22083AK  24101.18507465  .00000055  00000+0  21557-4 0  9992", 
                    "tle_2": "2 53165  53.2194  59.8334 0001662 101.0773 259.0406 15.08838082 96545",
                    "additionalargs": "",
                    "models":[
                        {
                            "iname": "ModelOrbit"
                        },
                        {
                            "iname": "ModelFovTimeBased",
                            "min_elevation": 25
                        },
                        {
                            "iname": "simplemodel"
                        }
                        
                    ]
                },

                {
                    "type": "SAT",
                    "iname": "SatelliteBasic",
                    "nodeid": 89,
                    "loglevel": "info",
                    "tle_1": "1 48574U 21041X   24101.40238224  .00003649  00000+0  26371-3 0  9992", 
                    "tle_2": "2 48574  53.0547 356.4380 0001212  90.9193 269.1935 15.06407237160760",
                    "additionalargs": "",
                    "models":[
                        {
                            "iname": "ModelOrbit"
                        },
                        {
                            "iname": "ModelFovTimeBased",
                            "min_elevation": 25
                        },
                        {
                            "iname": "simplemodel"
                        }
                        
                    ]
                },

                {
                    "type": "SAT",
                    "iname": "SatelliteBasic",
                    "nodeid": 91,
                    "loglevel": "info",
                    "tle_1": "1 52477U 22049AC  24101.55812110 -.00009594  00000+0 -58496-3 0  9996", 
                    "tle_2": "2 52477  53.2209 303.1550 0000467 358.0945   2.0045 15.08874504107153",
                    "additionalargs": "",
                    "models":[
                        {
                            "iname": "ModelOrbit"
                        },
                        {
                            "iname": "ModelFovTimeBased",
                            "min_elevation": 25
                        },
                        {
                            "iname": "simplemodel"
                        }
                        
                    ]
                },

                {
                    "type": "SAT",
                    "iname": "SatelliteBasic",
                    "nodeid": 93,
                    "loglevel": "info",
                    "tle_1": "1 59386U 24062N   24101.25001157 -.01243923  00000+0 -76469-2 0  9993", 
                    "tle_2": "2 59386  53.1652 277.2710 0000689  83.5442 229.4969 15.79334284  2492",
                    "additionalargs": "",
                    "models":[
                        {
                            "iname": "ModelOrbit"
                        },
                        {
                            "iname": "ModelFovTimeBased",
                            "min_elevation": 25
                        },
                        {
                            "iname": "simplemodel"
                        }
                        
                    ]
                },

                {
                    "type": "SAT",
                    "iname": "SatelliteBasic",
                    "nodeid": 95,
                    "loglevel": "info",
                    "tle_1": "1 58418U 23180S   24100.72869317  .00003447  00000+0  27006-3 0  9995", 
                    "tle_2": "2 58418  43.0014 253.9452 0001597 282.1617  77.9046 15.02539432 22336",
                    "additionalargs": "",
                    "models":[
                        {
                            "iname": "ModelOrbit"
                        },
                        {
                            "iname": "ModelFovTimeBased",
                            "min_elevation": 25
                        },
                        {
                            "iname": "simplemodel"
                        }
                        
                    ]
                },

                {
                    "type": "SAT",
                    "iname": "SatelliteBasic",
                    "nodeid": 97,
                    "loglevel": "info",
                    "tle_1": "1 58011U 23153W   24100.83152187 -.00001152  00000+0 -70248-4 0  9996", 
                    "tle_2": "2 58011  43.0028 266.6645 0001947 270.1830  89.8790 15.02524016 29740",
                    "additionalargs": "",
                    "models":[
                        {
                            "iname": "ModelOrbit"
                        },
                        {
                            "iname": "ModelFovTimeBased",
                            "min_elevation": 25
                        },
                        {
                            "iname": "simplemodel"
                        }
                        
                    ]
                },

                {
                    "type": "SAT",
                    "iname": "SatelliteBasic",
                    "nodeid": 99,
                    "loglevel": "info",
                    "tle_1": "1 58238U 23171J   24101.41812309 -.00000540  00000+0 -24908-4 0  9993", 
                    "tle_2": "2 58238  43.0028 120.5125 0000985 279.0294  81.0437 15.02540607 24702",
                    "additionalargs": "",
                    "models":[
                        {
                            "iname": "ModelOrbit"
                        },
                        {
                            "iname": "ModelFovTimeBased",
                            "min_elevation": 25
                        },
                        {
                            "iname": "simplemodel"
                        }
                        
                    ]
                },

                {
                    "type": "SAT",
                    "iname": "SatelliteBasic",
                    "nodeid": 101,
                    "loglevel": "info",
                    "tle_1": "1 48439U 21040M   24101.18490166  .00001501  00000+0  11962-3 0  9996", 
                    "tle_2": "2 48439  53.0542  77.3246 0001481  94.1624 265.9534 15.06401870162621",
                    "additionalargs": "",
                    "models":[
                        {
                            "iname": "ModelOrbit"
                        },
                        {
                            "iname": "ModelFovTimeBased",
                            "min_elevation": 25
                        },
                        {
                            "iname": "simplemodel"
                        }
                        
                    ]
                },

                {
                    "type": "SAT",
                    "iname": "SatelliteBasic",
                    "nodeid": 103,
                    "loglevel": "info",
                    "tle_1": "1 47753U 21017AH  24101.39223090  .00000807  00000+0  73045-4 0  9990", 
                    "tle_2": "2 47753  53.0539 106.3933 0001406  87.1953 272.9197 15.06412165171841",
                    "additionalargs": "",
                    "models":[
                        {
                            "iname": "ModelOrbit"
                        },
                        {
                            "iname": "ModelFovTimeBased",
                            "min_elevation": 25
                        },
                        {
                            "iname": "simplemodel"
                        }
                        
                    ]
                },

                {
                    "type": "SAT",
                    "iname": "SatelliteBasic",
                    "nodeid": 105,
                    "loglevel": "info",
                    "tle_1": "1 48145U 21027BF  24101.54519428  .00000498  00000+0  52316-4 0  9991", 
                    "tle_2": "2 48145  53.0550  45.7045 0001443  84.6791 275.4362 15.06401393167076",
                    "additionalargs": "",
                    "models":[
                        {
                            "iname": "ModelOrbit"
                        },
                        {
                            "iname": "ModelFovTimeBased",
                            "min_elevation": 25
                        },
                        {
                            "iname": "simplemodel"
                        }
                        
                    ]
                },

                {
                    "type": "SAT",
                    "iname": "SatelliteBasic",
                    "nodeid": 107,
                    "loglevel": "info",
                    "tle_1": "1 51462U 22010G   24101.46434579 -.00001611  00000+0 -83181-4 0  9998", 
                    "tle_2": "2 51462  53.2136 173.5855 0001147  85.6308 274.4815 15.08836094121882",
                    "additionalargs": "",
                    "models":[
                        {
                            "iname": "ModelOrbit"
                        },
                        {
                            "iname": "ModelFovTimeBased",
                            "min_elevation": 25
                        },
                        {
                            "iname": "simplemodel"
                        }
                        
                    ]
                },

                {
                    "type": "SAT",
                    "iname": "SatelliteBasic",
                    "nodeid": 109,
                    "loglevel": "info",
                    "tle_1": "1 58164U 23166Q   24101.58335648 -.00098504  00000+0 -35885-2 0  9990", 
                    "tle_2": "2 58164  53.1172 220.6836 0001209  87.8227 120.0595 15.28041529 26320",
                    "additionalargs": "",
                    "models":[
                        {
                            "iname": "ModelOrbit"
                        },
                        {
                            "iname": "ModelFovTimeBased",
                            "min_elevation": 25
                        },
                        {
                            "iname": "simplemodel"
                        }
                        
                    ]
                },

                {
                    "type": "SAT",
                    "iname": "SatelliteBasic",
                    "nodeid": 111,
                    "loglevel": "info",
                    "tle_1": "1 57505U 23113L   24101.58071832  .00000012  00000+0  15946-4 0  9995", 
                    "tle_2": "2 57505  43.0048 197.8958 0001412 252.8734 107.1954 15.02530841 38859",
                    "additionalargs": "",
                    "models":[
                        {
                            "iname": "ModelOrbit"
                        },
                        {
                            "iname": "ModelFovTimeBased",
                            "min_elevation": 25
                        },
                        {
                            "iname": "simplemodel"
                        }
                        
                    ]
                },

                {
                    "type": "SAT",
                    "iname": "SatelliteBasic",
                    "nodeid": 113,
                    "loglevel": "info",
                    "tle_1": "1 54864U 22177AW  24101.31451625  .00000409  00000+0  45362-4 0  9997", 
                    "tle_2": "2 54864  43.0031 314.9164 0001231 269.3873  90.6828 15.02531843 70948",
                    "additionalargs": "",
                    "models":[
                        {
                            "iname": "ModelOrbit"
                        },
                        {
                            "iname": "ModelFovTimeBased",
                            "min_elevation": 25
                        },
                        {
                            "iname": "simplemodel"
                        }
                        
                    ]
                },

                {
                    "type": "SAT",
                    "iname": "SatelliteBasic",
                    "nodeid": 115,
                    "loglevel": "info",
                    "tle_1": "1 53061U 22077U   24101.09632389  .00000726  00000+0  61072-4 0  9995", 
                    "tle_2": "2 53061  97.6544 282.9181 0001572  53.1517 306.9851 15.01268963 96682",
                    "additionalargs": "",
                    "models":[
                        {
                            "iname": "ModelOrbit"
                        },
                        {
                            "iname": "ModelFovTimeBased",
                            "min_elevation": 25
                        },
                        {
                            "iname": "simplemodel"
                        }
                        
                    ]
                },

                {
                    "type": "SAT",
                    "iname": "SatelliteBasic",
                    "nodeid": 117,
                    "loglevel": "info",
                    "tle_1": "1 56541U 23065AQ  24100.86472083  .00002138  00000+0  17326-3 0  9997", 
                    "tle_2": "2 56541  43.0046  60.5491 0001192 268.1440  91.9265 15.02539875 51354",
                    "additionalargs": "",
                    "models":[
                        {
                            "iname": "ModelOrbit"
                        },
                        {
                            "iname": "ModelFovTimeBased",
                            "min_elevation": 25
                        },
                        {
                            "iname": "simplemodel"
                        }
                        
                    ]
                },

                {
                    "type": "SAT",
                    "iname": "SatelliteBasic",
                    "nodeid": 119,
                    "loglevel": "info",
                    "tle_1": "1 59380U 24062G   24101.25001157 -.01194160  00000+0 -73564-2 0  9998", 
                    "tle_2": "2 59380  53.1659 277.2956 0000704  86.8347 214.3787 15.79173716  2169",
                    "additionalargs": "",
                    "models":[
                        {
                            "iname": "ModelOrbit"
                        },
                        {
                            "iname": "ModelFovTimeBased",
                            "min_elevation": 25
                        },
                        {
                            "iname": "simplemodel"
                        }
                        
                    ]
                },

                {
                    "type": "SAT",
                    "iname": "SatelliteBasic",
                    "nodeid": 121,
                    "loglevel": "info",
                    "tle_1": "1 53011U 22076AB  24100.40491086  .00002537  00000+0  17739-3 0  9992", 
                    "tle_2": "2 53011  53.2200 343.3304 0001481  88.7849 271.3312 15.08845584 97881",
                    "additionalargs": "",
                    "models":[
                        {
                            "iname": "ModelOrbit"
                        },
                        {
                            "iname": "ModelFovTimeBased",
                            "min_elevation": 25
                        },
                        {
                            "iname": "simplemodel"
                        }
                        
                    ]
                },

                {
                    "type": "SAT",
                    "iname": "SatelliteBasic",
                    "nodeid": 123,
                    "loglevel": "info",
                    "tle_1": "1 57634U 23122C   24101.50698527  .00000999  00000+0  88979-4 0  9996", 
                    "tle_2": "2 57634  43.0030 275.0617 0001728 276.6028  83.4618 15.02539281 37291",
                    "additionalargs": "",
                    "models":[
                        {
                            "iname": "ModelOrbit"
                        },
                        {
                            "iname": "ModelFovTimeBased",
                            "min_elevation": 25
                        },
                        {
                            "iname": "simplemodel"
                        }
                        
                    ]
                },

                {
                    "type": "SAT",
                    "iname": "SatelliteBasic",
                    "nodeid": 125,
                    "loglevel": "info",
                    "tle_1": "1 51993U 22025AP  24100.52865324  .00001724  00000+0  12638-3 0  9996", 
                    "tle_2": "2 51993  53.2178 297.7775 0001388  81.9698 278.1451 15.08838573115519",
                    "additionalargs": "",
                    "models":[
                        {
                            "iname": "ModelOrbit"
                        },
                        {
                            "iname": "ModelFovTimeBased",
                            "min_elevation": 25
                        },
                        {
                            "iname": "simplemodel"
                        }
                        
                    ]
                },

                {
                    "type": "SAT",
                    "iname": "SatelliteBasic",
                    "nodeid": 127,
                    "loglevel": "info",
                    "tle_1": "1 52671U 22053R   24100.87687137  .00000276  00000+0  35430-4 0  9990", 
                    "tle_2": "2 52671  53.2192  51.2079 0001296  97.9158 262.1981 15.08839212105549",
                    "additionalargs": "",
                    "models":[
                        {
                            "iname": "ModelOrbit"
                        },
                        {
                            "iname": "ModelFovTimeBased",
                            "min_elevation": 25
                        },
                        {
                            "iname": "simplemodel"
                        }
                        
                    ]
                },

                {
                    "type": "SAT",
                    "iname": "SatelliteBasic",
                    "nodeid": 129,
                    "loglevel": "info",
                    "tle_1": "1 51972U 22025S   24101.51836762  .00001457  00000+0  11671-3 0  9996", 
                    "tle_2": "2 51972  53.0523 285.0969 0001291  75.3904 284.7228 15.06399130116798",
                    "additionalargs": "",
                    "models":[
                        {
                            "iname": "ModelOrbit"
                        },
                        {
                            "iname": "ModelFovTimeBased",
                            "min_elevation": 25
                        },
                        {
                            "iname": "simplemodel"
                        }
                        
                    ]
                },

                {
                    "type": "SAT",
                    "iname": "SatelliteBasic",
                    "nodeid": 131,
                    "loglevel": "info",
                    "tle_1": "1 46567U 20070AM  24101.55026945  .00000295  00000+0  38694-4 0  9990", 
                    "tle_2": "2 46567  53.0557  50.6854 0001799  89.9725 270.1470 15.06398712194567",
                    "additionalargs": "",
                    "models":[
                        {
                            "iname": "ModelOrbit"
                        },
                        {
                            "iname": "ModelFovTimeBased",
                            "min_elevation": 25
                        },
                        {
                            "iname": "simplemodel"
                        }
                        
                    ]
                },

                {
                    "type": "SAT",
                    "iname": "SatelliteBasic",
                    "nodeid": 133,
                    "loglevel": "info",
                    "tle_1": "1 47724U 21017C   24101.07891791  .00001271  00000+0  10412-3 0  9996", 
                    "tle_2": "2 47724  53.0576  27.8010 0001407  88.7503 271.3647 15.06420348172927",
                    "additionalargs": "",
                    "models":[
                        {
                            "iname": "ModelOrbit"
                        },
                        {
                            "iname": "ModelFovTimeBased",
                            "min_elevation": 25
                        },
                        {
                            "iname": "simplemodel"
                        }
                        
                    ]
                },

                {
                    "type": "SAT",
                    "iname": "SatelliteBasic",
                    "nodeid": 135,
                    "loglevel": "info",
                    "tle_1": "1 55351U 23013W   24101.48344518  .00002795  00000+0  22174-3 0  9994", 
                    "tle_2": "2 55351  43.0041 133.9686 0001273 278.0117  82.0581 15.02558141 67119",
                    "additionalargs": "",
                    "models":[
                        {
                            "iname": "ModelOrbit"
                        },
                        {
                            "iname": "ModelFovTimeBased",
                            "min_elevation": 25
                        },
                        {
                            "iname": "simplemodel"
                        }
                        
                    ]
                },

                {
                    "type": "SAT",
                    "iname": "SatelliteBasic",
                    "nodeid": 137,
                    "loglevel": "info",
                    "tle_1": "1 58455U 23183U   24101.06802518  .00001387  00000+0  11772-3 0  9991", 
                    "tle_2": "2 58455  43.0025 239.4012 0002397 290.5478  69.5107 15.02543797 21644",
                    "additionalargs": "",
                    "models":[
                        {
                            "iname": "ModelOrbit"
                        },
                        {
                            "iname": "ModelFovTimeBased",
                            "min_elevation": 25
                        },
                        {
                            "iname": "simplemodel"
                        }
                        
                    ]
                },

                {
                    "type": "SAT",
                    "iname": "SatelliteBasic",
                    "nodeid": 139,
                    "loglevel": "info",
                    "tle_1": "1 46347U 20062Y   24101.05313374  .00003304  00000+0  24059-3 0  9990", 
                    "tle_2": "2 46347  53.0550 227.9211 0001388 100.0097 260.1049 15.06397891199814",
                    "additionalargs": "",
                    "models":[
                        {
                            "iname": "ModelOrbit"
                        },
                        {
                            "iname": "ModelFovTimeBased",
                            "min_elevation": 25
                        },
                        {
                            "iname": "simplemodel"
                        }
                        
                    ]
                },

                {
                    "type": "SAT",
                    "iname": "SatelliteBasic",
                    "nodeid": 141,
                    "loglevel": "info",
                    "tle_1": "1 56101U 23046J   24101.42231090 -.00001114  00000+0 -67449-4 0  9999", 
                    "tle_2": "2 56101  43.0051 353.2146 0001020 276.4342  83.6384 15.02529826 57568",
                    "additionalargs": "",
                    "models":[
                        {
                            "iname": "ModelOrbit"
                        },
                        {
                            "iname": "ModelFovTimeBased",
                            "min_elevation": 25
                        },
                        {
                            "iname": "simplemodel"
                        }
                        
                    ]
                },

                {
                    "type": "SAT",
                    "iname": "SatelliteBasic",
                    "nodeid": 143,
                    "loglevel": "info",
                    "tle_1": "1 56809U 23078AU  24101.31135531 -.00001510  00000+0 -11879-3 0  9995", 
                    "tle_2": "2 56809  70.0000 305.1649 0002785 273.1156  86.9684 14.98323879 48335",
                    "additionalargs": "",
                    "models":[
                        {
                            "iname": "ModelOrbit"
                        },
                        {
                            "iname": "ModelFovTimeBased",
                            "min_elevation": 25
                        },
                        {
                            "iname": "simplemodel"
                        }
                        
                    ]
                },

                {
                    "type": "SAT",
                    "iname": "SatelliteBasic",
                    "nodeid": 145,
                    "loglevel": "info",
                    "tle_1": "1 48294U 21036U   24101.38946904 -.00000491  00000+0 -14059-4 0  9998", 
                    "tle_2": "2 48294  53.0575 336.4056 0001410  89.5981 270.5170 15.06405507163642",
                    "additionalargs": "",
                    "models":[
                        {
                            "iname": "ModelOrbit"
                        },
                        {
                            "iname": "ModelFovTimeBased",
                            "min_elevation": 25
                        },
                        {
                            "iname": "simplemodel"
                        }
                        
                    ]
                },

                {
                    "type": "SAT",
                    "iname": "SatelliteBasic",
                    "nodeid": 147,
                    "loglevel": "info",
                    "tle_1": "1 55343U 23013N   24101.44030467  .00003581  00000+0  28004-3 0  9998", 
                    "tle_2": "2 55343  43.0019 134.5042 0001442 268.6800  91.3878 15.02532713 67108",
                    "additionalargs": "",
                    "models":[
                        {
                            "iname": "ModelOrbit"
                        },
                        {
                            "iname": "ModelFovTimeBased",
                            "min_elevation": 25
                        },
                        {
                            "iname": "simplemodel"
                        }
                        
                    ]
                },

                {
                    "type": "SAT",
                    "iname": "SatelliteBasic",
                    "nodeid": 149,
                    "loglevel": "info",
                    "tle_1": "1 53571U 22101AW  24100.84191223  .00000606  00000+0  56161-4 0  9998", 
                    "tle_2": "2 53571  53.2160 311.3169 0001235  84.8743 275.2390 15.08833194 91638",
                    "additionalargs": "",
                    "models":[
                        {
                            "iname": "ModelOrbit"
                        },
                        {
                            "iname": "ModelFovTimeBased",
                            "min_elevation": 25
                        },
                        {
                            "iname": "simplemodel"
                        }
                        
                    ]
                },

                {
                    "type": "SAT",
                    "iname": "SatelliteBasic",
                    "nodeid": 151,
                    "loglevel": "info",
                    "tle_1": "1 53392U 22097E   24101.20347500  .00000194  00000+0  30261-4 0  9990", 
                    "tle_2": "2 53392  53.2194  19.7440 0001330  84.2581 275.8563 15.08835601 92574",
                    "additionalargs": "",
                    "models":[
                        {
                            "iname": "ModelOrbit"
                        },
                        {
                            "iname": "ModelFovTimeBased",
                            "min_elevation": 25
                        },
                        {
                            "iname": "simplemodel"
                        }
                        
                    ]
                },

                {
                    "type": "SAT",
                    "iname": "SatelliteBasic",
                    "nodeid": 153,
                    "loglevel": "info",
                    "tle_1": "1 48384U 21038AH  24101.35853089  .00000660  00000+0  10307-4 0  9996", 
                    "tle_2": "2 48384  53.0541 229.5571 0001040 106.7147 253.3983 15.69717392162720",
                    "additionalargs": "",
                    "models":[
                        {
                            "iname": "ModelOrbit"
                        },
                        {
                            "iname": "ModelFovTimeBased",
                            "min_elevation": 25
                        },
                        {
                            "iname": "simplemodel"
                        }
                        
                    ]
                },

                {
                    "type": "SAT",
                    "iname": "SatelliteBasic",
                    "nodeid": 155,
                    "loglevel": "info",
                    "tle_1": "1 57892U 23146B   24100.87389314  .00001229  00000+0  10605-3 0  9995", 
                    "tle_2": "2 57892  43.0025 150.7314 0001005 272.6711  87.4016 15.02538381 31848",
                    "additionalargs": "",
                    "models":[
                        {
                            "iname": "ModelOrbit"
                        },
                        {
                            "iname": "ModelFovTimeBased",
                            "min_elevation": 25
                        },
                        {
                            "iname": "simplemodel"
                        }
                        
                    ]
                },

                {
                    "type": "SAT",
                    "iname": "SatelliteBasic",
                    "nodeid": 157,
                    "loglevel": "info",
                    "tle_1": "1 59367U 24060V   24101.58335648 -.01124805  00000+0 -69246-2 0  9993", 
                    "tle_2": "2 59367  43.0004 283.5132 0001837 270.1617  28.9382 15.78784734  2817",
                    "additionalargs": "",
                    "models":[
                        {
                            "iname": "ModelOrbit"
                        },
                        {
                            "iname": "ModelFovTimeBased",
                            "min_elevation": 25
                        },
                        {
                            "iname": "simplemodel"
                        }
                        
                    ]
                },

                {
                    "type": "SAT",
                    "iname": "SatelliteBasic",
                    "nodeid": 159,
                    "loglevel": "info",
                    "tle_1": "1 44922U 20001J   24101.10150950  .00002045  00000+0  15615-3 0  9994", 
                    "tle_2": "2 44922  53.0552 242.6968 0001317  93.3374 266.7766 15.06392022234550",
                    "additionalargs": "",
                    "models":[
                        {
                            "iname": "ModelOrbit"
                        },
                        {
                            "iname": "ModelFovTimeBased",
                            "min_elevation": 25
                        },
                        {
                            "iname": "simplemodel"
                        }
                        
                    ]
                },

                {
                    "type": "SAT",
                    "iname": "SatelliteBasic",
                    "nodeid": 161,
                    "loglevel": "info",
                    "tle_1": "1 45531U 20025A   24101.45535860  .00008129  00000+0  56389-3 0  9994", 
                    "tle_2": "2 45531  53.0547   1.1126 0001435  80.0179 280.0972 15.06404357219255",
                    "additionalargs": "",
                    "models":[
                        {
                            "iname": "ModelOrbit"
                        },
                        {
                            "iname": "ModelFovTimeBased",
                            "min_elevation": 25
                        },
                        {
                            "iname": "simplemodel"
                        }
                        
                    ]
                },

                {
                    "type": "SAT",
                    "iname": "SatelliteBasic",
                    "nodeid": 163,
                    "loglevel": "info",
                    "tle_1": "1 58967U 24031C   24101.53223346 -.00000127  00000+0  80661-5 0  9997", 
                    "tle_2": "2 58967  53.1611 299.4684 0000892  87.6981 272.4121 15.28009959  9640",
                    "additionalargs": "",
                    "models":[
                        {
                            "iname": "ModelOrbit"
                        },
                        {
                            "iname": "ModelFovTimeBased",
                            "min_elevation": 25
                        },
                        {
                            "iname": "simplemodel"
                        }
                        
                    ]
                },

                {
                    "type": "SAT",
                    "iname": "SatelliteBasic",
                    "nodeid": 165,
                    "loglevel": "info",
                    "tle_1": "1 51738U 22016AA  24101.33456082  .00005754  00000+0  37902-3 0  9998", 
                    "tle_2": "2 51738  53.2127 214.1547 0001730  84.1018 276.0171 15.08870904119246",
                    "additionalargs": "",
                    "models":[
                        {
                            "iname": "ModelOrbit"
                        },
                        {
                            "iname": "ModelFovTimeBased",
                            "min_elevation": 25
                        },
                        {
                            "iname": "simplemodel"
                        }
                        
                    ]
                },

                {
                    "type": "SAT",
                    "iname": "SatelliteBasic",
                    "nodeid": 167,
                    "loglevel": "info",
                    "tle_1": "1 52602U 22052E   24101.49282331  .00002382  00000+0  16779-3 0  9993", 
                    "tle_2": "2 52602  53.2169 173.4506 0001291  93.7371 266.3769 15.08823225105823",
                    "additionalargs": "",
                    "models":[
                        {
                            "iname": "ModelOrbit"
                        },
                        {
                            "iname": "ModelFovTimeBased",
                            "min_elevation": 25
                        },
                        {
                            "iname": "simplemodel"
                        }
                        
                    ]
                },

                {
                    "type": "SAT",
                    "iname": "SatelliteBasic",
                    "nodeid": 169,
                    "loglevel": "info",
                    "tle_1": "1 56427U 23061BF  24101.10404803  .00000116  00000+0  23632-4 0  9991", 
                    "tle_2": "2 56427  43.0043   7.8463 0001432 269.3707  90.6971 15.02534753 52253",
                    "additionalargs": "",
                    "models":[
                        {
                            "iname": "ModelOrbit"
                        },
                        {
                            "iname": "ModelFovTimeBased",
                            "min_elevation": 25
                        },
                        {
                            "iname": "simplemodel"
                        }
                        
                    ]
                },

                {
                    "type": "SAT",
                    "iname": "SatelliteBasic",
                    "nodeid": 171,
                    "loglevel": "info",
                    "tle_1": "1 54832U 22177N   24101.09410736  .00001684  00000+0  13972-3 0  9992", 
                    "tle_2": "2 54832  43.0047 316.7192 0001314 266.8968  93.1724 15.02539222 71033",
                    "additionalargs": "",
                    "models":[
                        {
                            "iname": "ModelOrbit"
                        },
                        {
                            "iname": "ModelFovTimeBased",
                            "min_elevation": 25
                        },
                        {
                            "iname": "simplemodel"
                        }
                        
                    ]
                },

                {
                    "type": "SAT",
                    "iname": "SatelliteBasic",
                    "nodeid": 173,
                    "loglevel": "info",
                    "tle_1": "1 51747U 22016AK  24100.59584966  .00001129  00000+0  89021-4 0  9990", 
                    "tle_2": "2 51747  53.2152 217.5227 0001941  86.7713 273.3501 15.08844697119157",
                    "additionalargs": "",
                    "models":[
                        {
                            "iname": "ModelOrbit"
                        },
                        {
                            "iname": "ModelFovTimeBased",
                            "min_elevation": 25
                        },
                        {
                            "iname": "simplemodel"
                        }
                        
                    ]
                },

                {
                    "type": "SAT",
                    "iname": "SatelliteBasic",
                    "nodeid": 175,
                    "loglevel": "info",
                    "tle_1": "1 48139U 21027AZ  24100.87435487  .00002200  00000+0  16663-3 0  9998", 
                    "tle_2": "2 48139  53.0557  48.7183 0001507  92.8494 267.2668 15.06387526167376",
                    "additionalargs": "",
                    "models":[
                        {
                            "iname": "ModelOrbit"
                        },
                        {
                            "iname": "ModelFovTimeBased",
                            "min_elevation": 25
                        },
                        {
                            "iname": "simplemodel"
                        }
                        
                    ]
                },

                {
                    "type": "SAT",
                    "iname": "SatelliteBasic",
                    "nodeid": 177,
                    "loglevel": "info",
                    "tle_1": "1 58527U 23191V   24101.52715286  .00000184  00000+0  28715-4 0  9996", 
                    "tle_2": "2 58527  43.0020 299.1549 0001544 277.1254  82.9413 15.02536550 20280",
                    "additionalargs": "",
                    "models":[
                        {
                            "iname": "ModelOrbit"
                        },
                        {
                            "iname": "ModelFovTimeBased",
                            "min_elevation": 25
                        },
                        {
                            "iname": "simplemodel"
                        }
                        
                    ]
                },

                {
                    "type": "SAT",
                    "iname": "SatelliteBasic",
                    "nodeid": 179,
                    "loglevel": "info",
                    "tle_1": "1 50837U 22001AL  24101.16436756  .00000265  00000+0  34712-4 0  9997", 
                    "tle_2": "2 50837  53.2179  64.9185 0001425  96.9169 263.1985 15.08847731126150",
                    "additionalargs": "",
                    "models":[
                        {
                            "iname": "ModelOrbit"
                        },
                        {
                            "iname": "ModelFovTimeBased",
                            "min_elevation": 25
                        },
                        {
                            "iname": "simplemodel"
                        }
                        
                    ]
                },

                {
                    "type": "SAT",
                    "iname": "SatelliteBasic",
                    "nodeid": 181,
                    "loglevel": "info",
                    "tle_1": "1 48569U 21041S   24100.53341320  .00001842  00000+0  14248-3 0  9994", 
                    "tle_2": "2 48569  53.0560  30.2487 0001431  91.5187 268.5966 15.06403168159828",
                    "additionalargs": "",
                    "models":[
                        {
                            "iname": "ModelOrbit"
                        },
                        {
                            "iname": "ModelFovTimeBased",
                            "min_elevation": 25
                        },
                        {
                            "iname": "simplemodel"
                        }
                        
                    ]
                },

                {
                    "type": "SAT",
                    "iname": "SatelliteBasic",
                    "nodeid": 183,
                    "loglevel": "info",
                    "tle_1": "1 46726U 20073BJ  24101.49911831  .00002398  00000+0  17984-3 0  9994", 
                    "tle_2": "2 46726  53.0538 135.9060 0001306  82.7268 277.3870 15.06399471192379",
                    "additionalargs": "",
                    "models":[
                        {
                            "iname": "ModelOrbit"
                        },
                        {
                            "iname": "ModelFovTimeBased",
                            "min_elevation": 25
                        },
                        {
                            "iname": "simplemodel"
                        }
                        
                    ]
                },

                {
                    "type": "SAT",
                    "iname": "SatelliteBasic",
                    "nodeid": 185,
                    "loglevel": "info",
                    "tle_1": "1 57135U 23090AL  24100.68992715  .00003627  00000+0  28335-3 0  9990", 
                    "tle_2": "2 57135  43.0024  99.9705 0001088 267.4574  92.6144 15.02542006 45221",
                    "additionalargs": "",
                    "models":[
                        {
                            "iname": "ModelOrbit"
                        },
                        {
                            "iname": "ModelFovTimeBased",
                            "min_elevation": 25
                        },
                        {
                            "iname": "simplemodel"
                        }
                        
                    ]
                },

                {
                    "type": "SAT",
                    "iname": "SatelliteBasic",
                    "nodeid": 187,
                    "loglevel": "info",
                    "tle_1": "1 48584U 21041AH  24100.83841651  .00001614  00000+0  12719-3 0  9994", 
                    "tle_2": "2 48584  53.0567  38.8778 0001505  92.2823 267.8338 15.06408626159724",
                    "additionalargs": "",
                    "models":[
                        {
                            "iname": "ModelOrbit"
                        },
                        {
                            "iname": "ModelFovTimeBased",
                            "min_elevation": 25
                        },
                        {
                            "iname": "simplemodel"
                        }
                        
                    ]
                },

                {
                    "type": "SAT",
                    "iname": "SatelliteBasic",
                    "nodeid": 189,
                    "loglevel": "info",
                    "tle_1": "1 52629U 22052AH  24101.53789351 -.00002572  00000+0 -14354-3 0  9991", 
                    "tle_2": "2 52629  53.2190 163.2112 0001634 101.5109 258.6067 15.08843707105972",
                    "additionalargs": "",
                    "models":[
                        {
                            "iname": "ModelOrbit"
                        },
                        {
                            "iname": "ModelFovTimeBased",
                            "min_elevation": 25
                        },
                        {
                            "iname": "simplemodel"
                        }
                        
                    ]
                },

                {
                    "type": "SAT",
                    "iname": "SatelliteBasic",
                    "nodeid": 191,
                    "loglevel": "info",
                    "tle_1": "1 53280U 22086AQ  24101.50564673  .00000886  00000+0  73710-4 0  9993", 
                    "tle_2": "2 53280  53.2208  33.0671 0001481  95.4402 264.6759 15.08848226 96264",
                    "additionalargs": "",
                    "models":[
                        {
                            "iname": "ModelOrbit"
                        },
                        {
                            "iname": "ModelFovTimeBased",
                            "min_elevation": 25
                        },
                        {
                            "iname": "simplemodel"
                        }
                        
                    ]
                },

                {
                    "type": "SAT",
                    "iname": "SatelliteBasic",
                    "nodeid": 193,
                    "loglevel": "info",
                    "tle_1": "1 53505U 22099AS  24101.21636675  .00002277  00000+0  18182-3 0  9994", 
                    "tle_2": "2 53505  97.6565 223.0401 0001200 245.2085 114.9014 15.01265530 91434",
                    "additionalargs": "",
                    "models":[
                        {
                            "iname": "ModelOrbit"
                        },
                        {
                            "iname": "ModelFovTimeBased",
                            "min_elevation": 25
                        },
                        {
                            "iname": "simplemodel"
                        }
                        
                    ]
                },

                {
                    "type": "SAT",
                    "iname": "SatelliteBasic",
                    "nodeid": 195,
                    "loglevel": "info",
                    "tle_1": "1 49421U 21104P   24101.43114821  .00000093  00000+0  23967-4 0  9992", 
                    "tle_2": "2 49421  53.2173 123.5345 0001477  95.6373 264.4788 15.08839127134290",
                    "additionalargs": "",
                    "models":[
                        {
                            "iname": "ModelOrbit"
                        },
                        {
                            "iname": "ModelFovTimeBased",
                            "min_elevation": 25
                        },
                        {
                            "iname": "simplemodel"
                        }
                        
                    ]
                },

                {
                    "type": "SAT",
                    "iname": "SatelliteBasic",
                    "nodeid": 197,
                    "loglevel": "info",
                    "tle_1": "1 53594U 22104G   24101.37642537  .00001026  00000+0  82527-4 0  9996", 
                    "tle_2": "2 53594  53.2164 138.9434 0001492  87.1376 272.9787 15.08844394 89509",
                    "additionalargs": "",
                    "models":[
                        {
                            "iname": "ModelOrbit"
                        },
                        {
                            "iname": "ModelFovTimeBased",
                            "min_elevation": 25
                        },
                        {
                            "iname": "simplemodel"
                        }
                        
                    ]
                },

                {
                    "type": "SAT",
                    "iname": "SatelliteBasic",
                    "nodeid": 199,
                    "loglevel": "info",
                    "tle_1": "1 50840U 22001AP  24101.17817585  .00000625  00000+0  57394-4 0  9996", 
                    "tle_2": "2 50840  53.2179  74.8584 0001484  82.0840 278.0320 15.08834988126095",
                    "additionalargs": "",
                    "models":[
                        {
                            "iname": "ModelOrbit"
                        },
                        {
                            "iname": "ModelFovTimeBased",
                            "min_elevation": 25
                        },
                        {
                            "iname": "simplemodel"
                        }
                        
                    ]
                },

                {
                    "type": "SAT",
                    "iname": "SatelliteBasic",
                    "nodeid": 201,
                    "loglevel": "info",
                    "tle_1": "1 59363U 24060R   24101.58335648 -.01090652  00000+0 -66862-2 0  9992", 
                    "tle_2": "2 59363  43.0005 283.5352 0001443 264.1780  26.1059 15.78803479  2814",
                    "additionalargs": "",
                    "models":[
                        {
                            "iname": "ModelOrbit"
                        },
                        {
                            "iname": "ModelFovTimeBased",
                            "min_elevation": 25
                        },
                        {
                            "iname": "simplemodel"
                        }
                        
                    ]
                },

                {
                    "type": "GS",
                    "iname": "GSBasic",
                    "nodeid": 202,
                    "loglevel": "info",
                    "latitude": 37.566500,
                    "longitude": 126.978000,
                    "elevation": 0.0,
                    "additionalargs": "",
                    "models":[
                        {
                            "iname": "ModelFovTimeBased",
                            "min_elevation": 25
                        }
                    ]
                }
                ]
            }
        ],
        "simtime":
        {
            "starttime": "2024-04-09 12:00:00",
            "endtime": "2024-04-16 12:00:00",
            "delta": 1
        },
        "simlogsetup":
        {
            "loghandler": "LoggerFileChunkwise",
            "logfolder": "imagingLogs",
            "logchunksize": 1000000
        }
}
    